[
  {
    "iso_code": "NGA",
    "name": "Nigeria",
    "sources": {
      "geoboundaries": {
        "type": "api",
        "max_level": 2
      },
      "osm": {
        "type": "api",
        "max_level": 4
      }
    },
    "recommended": {
      "0": "geoboundaries",
      "1": "geoboundaries",
      "2": "geoboundaries",
      "3": "geopode"
    },
    "_note": "Ward (ADM3) boundaries load via GeoPoDe — see fixtures/geopode_sources.json + `manage.py load_geopode_from_drive --iso NGA`. The old GRID3 'explore' URLs were never direct GeoJSON downloads, so that path was removed."
  },
  {
    "iso_code": "KEN",
    "name": "Kenya",
    "sources": {
      "geoboundaries": {
        "type": "api",
        "max_level": 2
      },
      "osm": {
        "type": "api",
        "max_level": 4
      }
    },
    "recommended": {
      "0": "geoboundaries",
      "1": "geoboundaries",
      "2": "geoboundaries"
    }
  },
  {
    "iso_code": "ETH",
    "name": "Ethiopia",
    "sources": {
      "geoboundaries": {
        "type": "api",
        "max_level": 2
      },
      "osm": {
        "type": "api",
        "max_level": 4
      }
    },
    "recommended": {
      "0": "geoboundaries",
      "1": "geoboundaries",
      "2": "geoboundaries"
    }
  },
  {
    "iso_code": "ZAF",
    "name": "South Africa",
    "sources": {
      "geoboundaries": {
        "type": "api",
        "max_level": 2
      },
      "osm": {
        "type": "api",
        "max_level": 4
      }
    },
    "recommended": {
      "0": "geoboundaries",
      "1": "geoboundaries",
      "2": "geoboundaries"
    }
  },
  {
    "iso_code": "ZMB",
    "name": "Zambia",
    "sources": {
      "geoboundaries": {
        "type": "api",
        "max_level": 2
      },
      "osm": {
        "type": "api",
        "max_level": 4
      }
    },
    "recommended": {
      "0": "geoboundaries",
      "1": "geoboundaries",
      "2": "geoboundaries"
    }
  },
  {
    "iso_code": "RWA",
    "name": "Rwanda",
    "sources": {
      "geoboundaries": {
        "type": "api",
        "max_level": 2
      },
      "osm": {
        "type": "api",
        "max_level": 4
      }
    },
    "recommended": {
      "0": "geoboundaries",
      "1": "geoboundaries",
      "2": "geoboundaries"
    }
  },
  {
    "iso_code": "UGA",
    "name": "Uganda",
    "sources": {
      "geoboundaries": {
        "type": "api",
        "max_level": 2
      },
      "osm": {
        "type": "api",
        "max_level": 4
      }
    },
    "recommended": {
      "0": "geoboundaries",
      "1": "geoboundaries",
      "2": "geoboundaries"
    }
  },
  {
    "iso_code": "MWI",
    "name": "Malawi",
    "sources": {
      "geoboundaries": {
        "type": "api",
        "max_level": 2
      },
      "osm": {
        "type": "api",
        "max_level": 4
      }
    },
    "recommended": {
      "0": "geoboundaries",
      "1": "geoboundaries",
      "2": "geoboundaries"
    }
  },
  {
    "iso_code": "TZA",
    "name": "Tanzania",
    "sources": {
      "geoboundaries": {
        "type": "api",
        "max_level": 2
      },
      "osm": {
        "type": "api",
        "max_level": 4
      }
    },
    "recommended": {
      "0": "geoboundaries",
      "1": "geoboundaries",
      "2": "geoboundaries"
    }
  },
  {
    "iso_code": "MOZ",
    "name": "Mozambique",
    "sources": {
      "geoboundaries": {
        "type": "api",
        "max_level": 2
      },
      "osm": {
        "type": "api",
        "max_level": 4
      }
    },
    "recommended": {
      "0": "geoboundaries",
      "1": "geoboundaries",
      "2": "geoboundaries"
    }
  },
  {
    "iso_code": "IND",
    "name": "India",
    "sources": {
      "geoboundaries": {
        "type": "api",
        "max_level": 2
      },
      "osm": {
        "type": "api",
        "max_level": 4
      }
    },
    "recommended": {
      "0": "geoboundaries",
      "1": "geoboundaries",
      "2": "geoboundaries"
    }
  },
  {
    "iso_code": "BGD",
    "name": "Bangladesh",
    "sources": {
      "geoboundaries": {
        "type": "api",
        "max_level": 2
      },
      "osm": {
        "type": "api",
        "max_level": 4
      }
    },
    "recommended": {
      "0": "geoboundaries",
      "1": "geoboundaries",
      "2": "geoboundaries"
    }
  },
  {
    "iso_code": "PAK",
    "name": "Pakistan",
    "sources": {
      "geoboundaries": {
        "type": "api",
        "max_level": 2
      },
      "osm": {
        "type": "api",
        "max_level": 4
      }
    },
    "recommended": {
      "0": "geoboundaries",
      "1": "geoboundaries",
      "2": "geoboundaries"
    }
  },
  {
    "iso_code": "PHL",
    "name": "Philippines",
    "sources": {
      "geoboundaries": {
        "type": "api",
        "max_level": 2
      },
      "osm": {
        "type": "api",
        "max_level": 4
      }
    },
    "recommended": {
      "0": "geoboundaries",
      "1": "geoboundaries",
      "2": "geoboundaries"
    }
  }
]
